README.md
setup.cfg
setup.py
python_window_recorder.egg-info/PKG-INFO
python_window_recorder.egg-info/SOURCES.txt
python_window_recorder.egg-info/dependency_links.txt
python_window_recorder.egg-info/requires.txt
python_window_recorder.egg-info/top_level.txt
window_recorder/__init__.py
window_recorder/capture/__init__.py
window_recorder/capture/d3d11.py
window_recorder/capture/d3dcapture.py
window_recorder/rotypes/__init__.py
window_recorder/rotypes/delegate.py
window_recorder/rotypes/export.py
window_recorder/rotypes/idldsl.py
window_recorder/rotypes/inspectable.py
window_recorder/rotypes/roapi.py
window_recorder/rotypes/types.py
window_recorder/rotypes/winstring.py
window_recorder/rotypes/Windows/__init__.py
window_recorder/rotypes/Windows/Foundation/Collections.py
window_recorder/rotypes/Windows/Foundation/__init__.py
window_recorder/rotypes/Windows/Globalization/__init__.py
window_recorder/rotypes/Windows/Graphics/__init__.py
window_recorder/rotypes/Windows/Graphics/Capture/__init__.py
window_recorder/rotypes/Windows/Graphics/DirectX/__init__.py
window_recorder/rotypes/Windows/Graphics/DirectX/Direct3D11/__init__.py
window_recorder/rotypes/Windows/Graphics/Imaging/__init__.py
window_recorder/rotypes/Windows/Media/__init__.py
window_recorder/rotypes/Windows/Media/Ocr/__init__.py
window_recorder/rotypes/Windows/Security/__init__.py
window_recorder/rotypes/Windows/Security/Cryptography/__init__.py
window_recorder/rotypes/Windows/Storage/__init__.py
window_recorder/rotypes/Windows/Storage/Streams/__init__.py