Metadata-Version: 2.1
Name: python-window-recorder
Version: 1.0
Summary: Background window recorder
Home-page: https://github.com/xjxckk/window-recorder/
